findmi/__init__.py
findmi/main.py
findmi-0.1.0.dist-info/entry_points.txt
findmi-0.1.0.dist-info/METADATA
findmi-0.1.0.dist-info/WHEEL
findmi-0.1.0.dist-info/RECORD
